nnfnd/__init__.py
nnfnd/classes.py
nnfnd/runner.py
nnfnd-1.0.2.dist-info/METADATA
nnfnd-1.0.2.dist-info/WHEEL
nnfnd-1.0.2.dist-info/top_level.txt
nnfnd-1.0.2.dist-info/RECORD
