Metadata-Version: 2.1
Name: nnfnd
Version: 1.0.2
Summary: Foundation library for ML and DL models
Home-page: UNKNOWN
Author: Alex Mogilevskiy
Author-email: dark.qvark@gmail.com
License: UNKNOWN
Platform: UNKNOWN
Requires-Python: >=3.6
Requires-Dist: tornado (==6.1)
